{
"type": "FeatureCollection",
"crs": { "type": "name", "properties": { "name": "urn:ogc:def:crs:OGC:1.3:CRS84" } },
"features": [
{ "type": "Feature", "properties": { "OBJECTID": 34, "Bornes": "B1", "lat": 6.804774703412634, "lon": -4.6125733189839435 }, "geometry": { "type": "Point", "coordinates": [ -4.612573318983944, 6.804774703412634 ] } },
{ "type": "Feature", "properties": { "OBJECTID": 34, "Bornes": "B2", "lat": 6.805025754527338, "lon": -4.612132937196936 }, "geometry": { "type": "Point", "coordinates": [ -4.612132937196936, 6.805025754527338 ] } },
{ "type": "Feature", "properties": { "OBJECTID": 34, "Bornes": "B3", "lat": 6.8046243585782014, "lon": -4.6112503624747951 }, "geometry": { "type": "Point", "coordinates": [ -4.611250362474795, 6.804624358578201 ] } },
{ "type": "Feature", "properties": { "OBJECTID": 34, "Bornes": "B4", "lat": 6.8041000644167617, "lon": -4.6113558432772059 }, "geometry": { "type": "Point", "coordinates": [ -4.611355843277206, 6.804100064416762 ] } },
{ "type": "Feature", "properties": { "OBJECTID": 34, "Bornes": "B5", "lat": 6.8034113947155639, "lon": -4.609951458086976 }, "geometry": { "type": "Point", "coordinates": [ -4.609951458086976, 6.803411394715564 ] } },
{ "type": "Feature", "properties": { "OBJECTID": 34, "Bornes": "B6", "lat": 6.8026348684043905, "lon": -4.6102007634707682 }, "geometry": { "type": "Point", "coordinates": [ -4.610200763470768, 6.80263486840439 ] } },
{ "type": "Feature", "properties": { "OBJECTID": 34, "Bornes": "B7", "lat": 6.8031259360121998, "lon": -4.6107864988153597 }, "geometry": { "type": "Point", "coordinates": [ -4.61078649881536, 6.8031259360122 ] } },
{ "type": "Feature", "properties": { "OBJECTID": 34, "Bornes": "B8", "lat": 6.8033634023616001, "lon": -4.6114244930302872 }, "geometry": { "type": "Point", "coordinates": [ -4.611424493030287, 6.8033634023616 ] } },
{ "type": "Feature", "properties": { "OBJECTID": 34, "Bornes": "B9", "lat": 6.8040314972254503, "lon": -4.6124323904200528 }, "geometry": { "type": "Point", "coordinates": [ -4.612432390420053, 6.80403149722545 ] } },
{ "type": "Feature", "properties": { "OBJECTID": 34, "Bornes": "B10", "lat": 6.8044229244684864, "lon": -4.6126104753615333 }, "geometry": { "type": "Point", "coordinates": [ -4.612610475361533, 6.804422924468486 ] } }
]
}
