{
"type": "FeatureCollection",
"crs": { "type": "name", "properties": { "name": "urn:ogc:def:crs:OGC:1.3:CRS84" } },
"features": [
{ "type": "Feature", "properties": { "OBJECTID": null, "Bornes": "B1", "lat": 6.8089320982030204, "lon": -4.621025546094419 }, "geometry": { "type": "Point", "coordinates": [ -4.621025546094419, 6.80893209820302 ] } },
{ "type": "Feature", "properties": { "OBJECTID": null, "Bornes": "B2", "lat": 6.8083945930147953, "lon": -4.6208878429523335 }, "geometry": { "type": "Point", "coordinates": [ -4.620887842952333, 6.808394593014795 ] } },
{ "type": "Feature", "properties": { "OBJECTID": null, "Bornes": "B3", "lat": 6.8077098634300848, "lon": -4.6212414332545713 }, "geometry": { "type": "Point", "coordinates": [ -4.621241433254571, 6.807709863430085 ] } },
{ "type": "Feature", "properties": { "OBJECTID": null, "Bornes": "B4", "lat": 6.8077860278000211, "lon": -4.6216182395671401 }, "geometry": { "type": "Point", "coordinates": [ -4.62161823956714, 6.807786027800021 ] } },
{ "type": "Feature", "properties": { "OBJECTID": null, "Bornes": "B5", "lat": 6.8086388418081656, "lon": -4.6215402543896698 }, "geometry": { "type": "Point", "coordinates": [ -4.62154025438967, 6.808638841808166 ] } }
]
}
