{
"type": "FeatureCollection",
"crs": { "type": "name", "properties": { "name": "urn:ogc:def:crs:OGC:1.3:CRS84" } },
"features": [
{ "type": "Feature", "properties": { "OBJECTID": 54, "Bornes": "B1", "lat": 6.8064377120075736, "lon": -4.6269619658966494 }, "geometry": { "type": "Point", "coordinates": [ -4.626961965896649, 6.806437712007574 ] } },
{ "type": "Feature", "properties": { "OBJECTID": 54, "Bornes": "B2", "lat": 6.8063481819173948, "lon": -4.6262820793693917 }, "geometry": { "type": "Point", "coordinates": [ -4.626282079369392, 6.806348181917395 ] } },
{ "type": "Feature", "properties": { "OBJECTID": 54, "Bornes": "B3", "lat": 6.8064748205636585, "lon": -4.6256854699917636 }, "geometry": { "type": "Point", "coordinates": [ -4.625685469991764, 6.806474820563658 ] } },
{ "type": "Feature", "properties": { "OBJECTID": 54, "Bornes": "B4", "lat": 6.806172637546541, "lon": -4.6261673120947364 }, "geometry": { "type": "Point", "coordinates": [ -4.626167312094736, 6.806172637546541 ] } }
]
}
