{
"type": "FeatureCollection",
"crs": { "type": "name", "properties": { "name": "urn:ogc:def:crs:OGC:1.3:CRS84" } },
"features": [
{ "type": "Feature", "properties": { "OBJECTID": null, "Bornes": "B1", "lat": 6.804774703412634, "lon": -4.6125733189839435 }, "geometry": { "type": "Point", "coordinates": [ -4.612573318983944, 6.804774703412634 ] } },
{ "type": "Feature", "properties": { "OBJECTID": null, "Bornes": "B2", "lat": 6.8054233036750489, "lon": -4.6134362023864917 }, "geometry": { "type": "Point", "coordinates": [ -4.613436202386492, 6.805423303675049 ] } },
{ "type": "Feature", "properties": { "OBJECTID": null, "Bornes": "B3", "lat": 6.8056115734294389, "lon": -4.6147163702246008 }, "geometry": { "type": "Point", "coordinates": [ -4.614716370224601, 6.805611573429439 ] } },
{ "type": "Feature", "properties": { "OBJECTID": null, "Bornes": "B4", "lat": 6.8058253454407653, "lon": -4.6143758023828587 }, "geometry": { "type": "Point", "coordinates": [ -4.614375802382859, 6.805825345440765 ] } },
{ "type": "Feature", "properties": { "OBJECTID": null, "Bornes": "B5", "lat": 6.8067016782007332, "lon": -4.6135593168502247 }, "geometry": { "type": "Point", "coordinates": [ -4.613559316850225, 6.806701678200733 ] } },
{ "type": "Feature", "properties": { "OBJECTID": null, "Bornes": "B6", "lat": 6.8068349893241944, "lon": -4.6132295700873751 }, "geometry": { "type": "Point", "coordinates": [ -4.613229570087375, 6.806834989324194 ] } },
{ "type": "Feature", "properties": { "OBJECTID": null, "Bornes": "B7", "lat": 6.8070247866292073, "lon": -4.6123691474528741 }, "geometry": { "type": "Point", "coordinates": [ -4.612369147452874, 6.807024786629207 ] } },
{ "type": "Feature", "properties": { "OBJECTID": null, "Bornes": "B8", "lat": 6.8071951395593908, "lon": -4.6116800923806904 }, "geometry": { "type": "Point", "coordinates": [ -4.61168009238069, 6.807195139559391 ] } },
{ "type": "Feature", "properties": { "OBJECTID": null, "Bornes": "B9", "lat": 6.8071955036780878, "lon": -4.6114650554380434 }, "geometry": { "type": "Point", "coordinates": [ -4.611465055438043, 6.807195503678088 ] } },
{ "type": "Feature", "properties": { "OBJECTID": null, "Bornes": "B10", "lat": 6.8067352626811024, "lon": -4.6110399305474461 }, "geometry": { "type": "Point", "coordinates": [ -4.611039930547446, 6.806735262681102 ] } },
{ "type": "Feature", "properties": { "OBJECTID": null, "Bornes": "B11", "lat": 6.806326910712813, "lon": -4.6105105906644166 }, "geometry": { "type": "Point", "coordinates": [ -4.610510590664417, 6.806326910712813 ] } },
{ "type": "Feature", "properties": { "OBJECTID": null, "Bornes": "B12", "lat": 6.806241403543603, "lon": -4.6111623215993083 }, "geometry": { "type": "Point", "coordinates": [ -4.611162321599308, 6.806241403543603 ] } },
{ "type": "Feature", "properties": { "OBJECTID": null, "Bornes": "B13", "lat": 6.8061753537472436, "lon": -4.6112935122726464 }, "geometry": { "type": "Point", "coordinates": [ -4.611293512272646, 6.806175353747244 ] } },
{ "type": "Feature", "properties": { "OBJECTID": 51.0, "Bornes": "B14", "lat": 6.8055615482299379, "lon": -4.6118518923647125 }, "geometry": { "type": "Point", "coordinates": [ -4.611851892364712, 6.805561548229938 ] } },
{ "type": "Feature", "properties": { "OBJECTID": null, "Bornes": "B15", "lat": 6.805025754527338, "lon": -4.612132937196936 }, "geometry": { "type": "Point", "coordinates": [ -4.612132937196936, 6.805025754527338 ] } }
]
}
